websuper/__init__.py
websuper/api.py
websuper/cli.py
websuper/config.py
websuper/tunnel.py
websuper-1.0.0.dist-info/METADATA
websuper-1.0.0.dist-info/WHEEL
websuper-1.0.0.dist-info/entry_points.txt
websuper-1.0.0.dist-info/top_level.txt
websuper-1.0.0.dist-info/RECORD
