Metadata-Version: 2.4
Name: websuper
Version: 1.0.0
Summary: Ngrok-like tunneling tool
Requires-Dist: requests
Requires-Dist: flask
